[
    {
        "dac_front": -3600,
        "dac_rear": -3600,
        "max31865_front": -16.15625,
        "max31865_rear": -16.53125,
        "sht31_inside": 24.55500030517578,
        "sht31_outside": 24.54199981689453,
        "time_s": 8.756
    },
    {
        "dac_front": -3600,
        "dac_rear": -3600,
        "max31865_front": -16.15625,
        "max31865_rear": -16.53125,
        "sht31_inside": 24.45599937438965,
        "sht31_outside": 24.44300079345703,
        "time_s": 9.759
    },
    {
        "dac_front": -3600,
        "dac_rear": -3600,
        "max31865_front": -16.1875,
        "max31865_rear": -16.5,
        "sht31_inside": 24.511999130249023,
        "sht31_outside": 24.486000061035156,
        "time_s": 10.817
    },
    {
        "dac_front": -3600,
        "dac_rear": -3600,
        "max31865_front": -16.21875,
        "max31865_rear": -16.53125,
        "sht31_inside": 24.569000244140625,
        "sht31_outside": 24.527999877929688,
        "time_s": 11.822
    },
    {
        "dac_front": -3600,
        "dac_rear": -3600,
        "max31865_front": -16.15625,
        "max31865_rear": -16.53125,
        "sht31_inside": 24.486000061035156,
        "sht31_outside": 24.570999145507812,
        "time_s": 12.83
    },
    {
        "dac_front": -3600,
        "dac_rear": -3600,
        "max31865_front": -16.15625,
        "max31865_rear": -16.53125,
        "sht31_inside": 24.413999557495117,
        "sht31_outside": 24.44300079345703,
        "time_s": 14.861
    },
    {
        "dac_front": -3700,
        "dac_rear": -3600,
        "max31865_front": -16.1875,
        "max31865_rear": -16.5625,
        "sht31_inside": 24.486000061035156,
        "sht31_outside": 24.511999130249023,
        "time_s": 15.848
    },
    {
        "dac_front": -3700,
        "dac_rear": -3700,
        "max31865_front": -16.1875,
        "max31865_rear": -16.5625,
        "sht31_inside": 24.499000549316406,
        "sht31_outside": 24.55500030517578,
        "time_s": 16.854
    },
    {
        "dac_front": -3700,
        "dac_rear": -3700,
        "max31865_front": -16.15625,
        "max31865_rear": -16.5,
        "sht31_inside": 24.427000045776367,
        "sht31_outside": 24.54199981689453,
        "time_s": 17.861
    },
    {
        "dac_front": -3700,
        "dac_rear": -3700,
        "max31865_front": -16.1875,
        "max31865_rear": -16.53125,
        "sht31_inside": 24.486000061035156,
        "sht31_outside": 24.527999877929688,
        "time_s": 18.868
    },
    {
        "dac_front": -3700,
        "dac_rear": -3700,
        "max31865_front": -16.1875,
        "max31865_rear": -16.53125,
        "sht31_inside": 24.527999877929688,
        "sht31_outside": 24.486000061035156,
        "time_s": 19.853
    },
    {
        "dac_front": -3700,
        "dac_rear": -3700,
        "max31865_front": -16.1875,
        "max31865_rear": -16.5,
        "sht31_inside": 24.527999877929688,
        "sht31_outside": 24.62700080871582,
        "time_s": 20.898
    },
    {
        "dac_front": -3700,
        "dac_rear": -3700,
        "max31865_front": -16.125,
        "max31865_rear": -16.5,
        "sht31_inside": 24.527999877929688,
        "sht31_outside": 24.570999145507812,
        "time_s": 21.904
    },
    {
        "dac_front": -3700,
        "dac_rear": -3700,
        "max31865_front": -16.15625,
        "max31865_rear": -16.5625,
        "sht31_inside": 24.625,
        "sht31_outside": 24.499000549316406,
        "time_s": 22.911
    },
    {
        "dac_front": -3700,
        "dac_rear": -3700,
        "max31865_front": -16.125,
        "max31865_rear": -16.53125,
        "sht31_inside": 24.511999130249023,
        "sht31_outside": 24.55500030517578,
        "time_s": 24.893
    },
    {
        "dac_front": -3700,
        "dac_rear": -3700,
        "max31865_front": -16.1875,
        "max31865_rear": -16.53125,
        "sht31_inside": 24.54199981689453,
        "sht31_outside": 24.597999572753906,
        "time_s": 25.915
    },
    {
        "dac_front": -3700,
        "dac_rear": -3700,
        "max31865_front": -16.15625,
        "max31865_rear": -16.5625,
        "sht31_inside": 24.440000534057617,
        "sht31_outside": 24.55500030517578,
        "time_s": 26.922
    },
    {
        "dac_front": -3700,
        "dac_rear": -3700,
        "max31865_front": -16.1875,
        "max31865_rear": -16.5,
        "sht31_inside": 24.569000244140625,
        "sht31_outside": 24.54199981689453,
        "time_s": 27.943
    },
    {
        "dac_front": -3700,
        "dac_rear": -3700,
        "max31865_front": -16.15625,
        "max31865_rear": -16.53125,
        "sht31_inside": 24.54199981689453,
        "sht31_outside": 24.472000122070312,
        "time_s": 28.933
    },
    {
        "dac_front": -3700,
        "dac_rear": -3700,
        "max31865_front": -16.1875,
        "max31865_rear": -16.53125,
        "sht31_inside": 24.486000061035156,
        "sht31_outside": 24.511999130249023,
        "time_s": 29.939
    },
    {
        "dac_front": -3700,
        "dac_rear": -3700,
        "max31865_front": -16.15625,
        "max31865_rear": -16.53125,
        "sht31_inside": 24.55500030517578,
        "sht31_outside": 24.472000122070312,
        "time_s": 30.961
    },
    {
        "dac_front": -3700,
        "dac_rear": -3700,
        "max31865_front": -16.15625,
        "max31865_rear": -16.53125,
        "sht31_inside": 24.486000061035156,
        "sht31_outside": 24.65399932861328,
        "time_s": 32.962
    },
    {
        "dac_front": -3700,
        "dac_rear": -3700,
        "max31865_front": -16.15625,
        "max31865_rear": -16.53125,
        "sht31_inside": 24.641000747680664,
        "sht31_outside": 24.54199981689453,
        "time_s": 33.964
    },
    {
        "dac_front": -3700,
        "dac_rear": -3700,
        "max31865_front": -16.15625,
        "max31865_rear": -16.53125,
        "sht31_inside": 24.486000061035156,
        "sht31_outside": 24.54199981689453,
        "time_s": 34.97
    },
    {
        "dac_front": -3700,
        "dac_rear": -3700,
        "max31865_front": -16.15625,
        "max31865_rear": -16.53125,
        "sht31_inside": 24.611000061035156,
        "sht31_outside": 24.641000747680664,
        "time_s": 35.978
    },
    {
        "dac_front": -3700,
        "dac_rear": -3700,
        "max31865_front": -16.1875,
        "max31865_rear": -16.53125,
        "sht31_inside": 24.611000061035156,
        "sht31_outside": 24.54199981689453,
        "time_s": 36.985
    },
    {
        "dac_front": -3700,
        "dac_rear": -3700,
        "max31865_front": -16.15625,
        "max31865_rear": -16.53125,
        "sht31_inside": 24.569000244140625,
        "sht31_outside": 24.641000747680664,
        "time_s": 38.022
    },
    {
        "dac_front": -3700,
        "dac_rear": -3700,
        "max31865_front": -16.15625,
        "max31865_rear": -16.5,
        "sht31_inside": 24.54199981689453,
        "sht31_outside": 24.499000549316406,
        "time_s": 39.013
    },
    {
        "dac_front": -3700,
        "dac_rear": -3700,
        "max31865_front": -16.15625,
        "max31865_rear": -16.5,
        "sht31_inside": 24.584999084472656,
        "sht31_outside": 24.611000061035156,
        "time_s": 40.02
    },
    {
        "dac_front": -3700,
        "dac_rear": -3700,
        "max31865_front": -16.15625,
        "max31865_rear": -16.53125,
        "sht31_inside": 24.499000549316406,
        "sht31_outside": 24.597999572753906,
        "time_s": 41.027
    },
    {
        "dac_front": -3700,
        "dac_rear": -3700,
        "max31865_front": -16.15625,
        "max31865_rear": -16.53125,
        "sht31_inside": 24.611000061035156,
        "sht31_outside": 24.511999130249023,
        "time_s": 42.033
    },
    {
        "dac_front": -3700,
        "dac_rear": -3700,
        "max31865_front": -16.1875,
        "max31865_rear": -16.5,
        "sht31_inside": 24.55500030517578,
        "sht31_outside": 24.611000061035156,
        "time_s": 43.04
    },
    {
        "dac_front": -3700,
        "dac_rear": -3700,
        "max31865_front": -16.15625,
        "max31865_rear": -16.53125,
        "sht31_inside": 24.569000244140625,
        "sht31_outside": 24.55500030517578,
        "time_s": 44.047
    },
    {
        "dac_front": -3700,
        "dac_rear": -3700,
        "max31865_front": -16.1875,
        "max31865_rear": -16.53125,
        "sht31_inside": 24.597999572753906,
        "sht31_outside": 24.597999572753906,
        "time_s": 45.069
    },
    {
        "dac_front": -3700,
        "dac_rear": -3700,
        "max31865_front": -16.1875,
        "max31865_rear": -16.53125,
        "sht31_inside": 24.54199981689453,
        "sht31_outside": 24.55500030517578,
        "time_s": 46.106
    },
    {
        "dac_front": -3700,
        "dac_rear": -3700,
        "max31865_front": -16.1875,
        "max31865_rear": -16.53125,
        "sht31_inside": 24.569000244140625,
        "sht31_outside": 24.584999084472656,
        "time_s": 47.113
    },
    {
        "dac_front": -3700,
        "dac_rear": -3700,
        "max31865_front": -16.15625,
        "max31865_rear": -16.53125,
        "sht31_inside": 24.611000061035156,
        "sht31_outside": 24.511999130249023,
        "time_s": 48.119
    },
    {
        "dac_front": -3700,
        "dac_rear": -3700,
        "max31865_front": -16.15625,
        "max31865_rear": -16.5,
        "sht31_inside": 24.569000244140625,
        "sht31_outside": 24.597999572753906,
        "time_s": 49.11
    },
    {
        "dac_front": -3700,
        "dac_rear": -3700,
        "max31865_front": -16.15625,
        "max31865_rear": -16.53125,
        "sht31_inside": 24.584999084472656,
        "sht31_outside": 24.611000061035156,
        "time_s": 50.116
    },
    {
        "dac_front": -3700,
        "dac_rear": -3700,
        "max31865_front": -16.1875,
        "max31865_rear": -16.5625,
        "sht31_inside": 24.499000549316406,
        "sht31_outside": 24.683000564575195,
        "time_s": 51.124
    },
    {
        "dac_front": -3700,
        "dac_rear": -3700,
        "max31865_front": -16.15625,
        "max31865_rear": -16.53125,
        "sht31_inside": 24.569000244140625,
        "sht31_outside": 24.584999084472656,
        "time_s": 52.114
    },
    {
        "dac_front": -3700,
        "dac_rear": -3700,
        "max31865_front": -16.15625,
        "max31865_rear": -16.5,
        "sht31_inside": 24.55500030517578,
        "sht31_outside": 24.641000747680664,
        "time_s": 53.12
    },
    {
        "dac_front": -3700,
        "dac_rear": -3700,
        "max31865_front": -16.125,
        "max31865_rear": -16.53125,
        "sht31_inside": 24.54199981689453,
        "sht31_outside": 24.584999084472656,
        "time_s": 54.127
    },
    {
        "dac_front": -3700,
        "dac_rear": -3700,
        "max31865_front": -16.15625,
        "max31865_rear": -16.5625,
        "sht31_inside": 24.55500030517578,
        "sht31_outside": 24.597999572753906,
        "time_s": 55.18
    },
    {
        "dac_front": -3700,
        "dac_rear": -3700,
        "max31865_front": -16.1875,
        "max31865_rear": -16.53125,
        "sht31_inside": 24.65399932861328,
        "sht31_outside": 24.597999572753906,
        "time_s": 56.209
    },
    {
        "dac_front": -3700,
        "dac_rear": -3700,
        "max31865_front": -16.1875,
        "max31865_rear": -16.53125,
        "sht31_inside": 24.584999084472656,
        "sht31_outside": 24.611000061035156,
        "time_s": 57.217
    },
    {
        "dac_front": -3700,
        "dac_rear": -3700,
        "max31865_front": -16.1875,
        "max31865_rear": -16.53125,
        "sht31_inside": 24.65399932861328,
        "sht31_outside": 24.54199981689453,
        "time_s": 59.231
    },
    {
        "dac_front": -3700,
        "dac_rear": -3700,
        "max31865_front": -16.1875,
        "max31865_rear": -16.53125,
        "sht31_inside": 24.611000061035156,
        "sht31_outside": 24.584999084472656,
        "time_s": 60.213
    },
    {
        "dac_front": -3700,
        "dac_rear": -3700,
        "max31865_front": -16.15625,
        "max31865_rear": -16.5625,
        "sht31_inside": 24.611000061035156,
        "sht31_outside": 24.54199981689453,
        "time_s": 61.243
    },
    {
        "dac_front": -3700,
        "dac_rear": -3700,
        "max31865_front": -16.15625,
        "max31865_rear": -16.5625,
        "sht31_inside": 24.55500030517578,
        "sht31_outside": 24.584999084472656,
        "time_s": 62.228
    },
    {
        "dac_front": -3700,
        "dac_rear": -3700,
        "max31865_front": -16.1875,
        "max31865_rear": -16.53125,
        "sht31_inside": 24.625,
        "sht31_outside": 24.54199981689453,
        "time_s": 63.235
    },
    {
        "dac_front": -3700,
        "dac_rear": -3700,
        "max31865_front": -16.1875,
        "max31865_rear": -16.53125,
        "sht31_inside": 24.722999572753906,
        "sht31_outside": 24.527999877929688,
        "time_s": 64.265
    },
    {
        "dac_front": -3700,
        "dac_rear": -3700,
        "max31865_front": -16.1875,
        "max31865_rear": -16.53125,
        "sht31_inside": 24.65399932861328,
        "sht31_outside": 24.55500030517578,
        "time_s": 65.249
    },
    {
        "dac_front": -3700,
        "dac_rear": -3700,
        "max31865_front": -16.1875,
        "max31865_rear": -16.53125,
        "sht31_inside": 24.584999084472656,
        "sht31_outside": 24.597999572753906,
        "time_s": 66.256
    },
    {
        "dac_front": -3700,
        "dac_rear": -3700,
        "max31865_front": -16.15625,
        "max31865_rear": -16.53125,
        "sht31_inside": 24.683000564575195,
        "sht31_outside": 24.55500030517578,
        "time_s": 67.263
    },
    {
        "dac_front": -3700,
        "dac_rear": -3700,
        "max31865_front": -16.1875,
        "max31865_rear": -16.5625,
        "sht31_inside": 24.683000564575195,
        "sht31_outside": 24.670000076293945,
        "time_s": 68.292
    },
    {
        "dac_front": -3700,
        "dac_rear": -3700,
        "max31865_front": -16.15625,
        "max31865_rear": -16.5625,
        "sht31_inside": 24.65399932861328,
        "sht31_outside": 24.641000747680664,
        "time_s": 69.299
    },
    {
        "dac_front": -3700,
        "dac_rear": -3700,
        "max31865_front": -16.15625,
        "max31865_rear": -16.53125,
        "sht31_inside": 24.569000244140625,
        "sht31_outside": 24.54199981689453,
        "time_s": 70.307
    },
    {
        "dac_front": -3700,
        "dac_rear": -3700,
        "max31865_front": -16.1875,
        "max31865_rear": -16.59375,
        "sht31_inside": 24.641000747680664,
        "sht31_outside": 24.641000747680664,
        "time_s": 71.315
    },
    {
        "dac_front": -3700,
        "dac_rear": -3700,
        "max31865_front": -16.1875,
        "max31865_rear": -16.5625,
        "sht31_inside": 24.611000061035156,
        "sht31_outside": 24.611000061035156,
        "time_s": 72.322
    },
    {
        "dac_front": -3700,
        "dac_rear": -3700,
        "max31865_front": -16.15625,
        "max31865_rear": -16.5625,
        "sht31_inside": 24.625,
        "sht31_outside": 24.55500030517578,
        "time_s": 75.316
    },
    {
        "dac_front": -3700,
        "dac_rear": -3700,
        "max31865_front": -16.1875,
        "max31865_rear": -16.53125,
        "sht31_inside": 24.65399932861328,
        "sht31_outside": 24.641000747680664,
        "time_s": 76.32
    },
    {
        "dac_front": -3700,
        "dac_rear": -3700,
        "max31865_front": -16.15625,
        "max31865_rear": -16.5625,
        "sht31_inside": 24.597999572753906,
        "sht31_outside": 24.670000076293945,
        "time_s": 77.349
    },
    {
        "dac_front": -3700,
        "dac_rear": -3700,
        "max31865_front": -16.15625,
        "max31865_rear": -16.5625,
        "sht31_inside": 24.722999572753906,
        "sht31_outside": 24.641000747680664,
        "time_s": 78.355
    },
    {
        "dac_front": -3700,
        "dac_rear": -3700,
        "max31865_front": -16.15625,
        "max31865_rear": -16.5625,
        "sht31_inside": 24.65399932861328,
        "sht31_outside": 24.670000076293945,
        "time_s": 80.4
    },
    {
        "dac_front": -3700,
        "dac_rear": -3700,
        "max31865_front": -16.15625,
        "max31865_rear": -16.5625,
        "sht31_inside": 24.625,
        "sht31_outside": 24.641000747680664,
        "time_s": 81.348
    },
    {
        "dac_front": -3700,
        "dac_rear": -3700,
        "max31865_front": -16.15625,
        "max31865_rear": -16.5625,
        "sht31_inside": 24.709999084472656,
        "sht31_outside": 24.54199981689453,
        "time_s": 82.355
    },
    {
        "dac_front": -3700,
        "dac_rear": -3700,
        "max31865_front": -16.15625,
        "max31865_rear": -16.5625,
        "sht31_inside": 24.597999572753906,
        "sht31_outside": 24.62700080871582,
        "time_s": 83.362
    },
    {
        "dac_front": -3700,
        "dac_rear": -3700,
        "max31865_front": -16.15625,
        "max31865_rear": -16.53125,
        "sht31_inside": 24.55500030517578,
        "sht31_outside": 24.55500030517578,
        "time_s": 84.369
    },
    {
        "dac_front": -3700,
        "dac_rear": -3700,
        "max31865_front": -16.125,
        "max31865_rear": -16.5625,
        "sht31_inside": 24.641000747680664,
        "sht31_outside": 24.670000076293945,
        "time_s": 85.396
    },
    {
        "dac_front": -3700,
        "dac_rear": -3700,
        "max31865_front": -16.15625,
        "max31865_rear": -16.5625,
        "sht31_inside": 24.683000564575195,
        "sht31_outside": 24.670000076293945,
        "time_s": 86.404
    },
    {
        "dac_front": -3700,
        "dac_rear": -3700,
        "max31865_front": -16.125,
        "max31865_rear": -16.5625,
        "sht31_inside": 24.641000747680664,
        "sht31_outside": 24.69700050354004,
        "time_s": 87.411
    },
    {
        "dac_front": -3700,
        "dac_rear": -3700,
        "max31865_front": -16.15625,
        "max31865_rear": -16.53125,
        "sht31_inside": 24.641000747680664,
        "sht31_outside": 24.584999084472656,
        "time_s": 88.417
    },
    {
        "dac_front": -3700,
        "dac_rear": -3700,
        "max31865_front": -16.15625,
        "max31865_rear": -16.5625,
        "sht31_inside": 24.597999572753906,
        "sht31_outside": 24.597999572753906,
        "time_s": 89.425
    },
    {
        "dac_front": -3700,
        "dac_rear": -3700,
        "max31865_front": -16.15625,
        "max31865_rear": -16.5625,
        "sht31_inside": 24.569000244140625,
        "sht31_outside": 24.641000747680664,
        "time_s": 90.416
    },
    {
        "dac_front": -3700,
        "dac_rear": -3700,
        "max31865_front": -16.15625,
        "max31865_rear": -16.5625,
        "sht31_inside": 24.584999084472656,
        "sht31_outside": 24.611000061035156,
        "time_s": 91.461
    },
    {
        "dac_front": -3700,
        "dac_rear": -3700,
        "max31865_front": -16.1875,
        "max31865_rear": -16.53125,
        "sht31_inside": 24.611000061035156,
        "sht31_outside": 24.597999572753906,
        "time_s": 92.485
    },
    {
        "dac_front": -3700,
        "dac_rear": -3700,
        "max31865_front": -16.15625,
        "max31865_rear": -16.53125,
        "sht31_inside": 24.597999572753906,
        "sht31_outside": 24.597999572753906,
        "time_s": 93.476
    },
    {
        "dac_front": -3700,
        "dac_rear": -3700,
        "max31865_front": -16.15625,
        "max31865_rear": -16.5625,
        "sht31_inside": 24.597999572753906,
        "sht31_outside": 24.641000747680664,
        "time_s": 94.484
    },
    {
        "dac_front": -3700,
        "dac_rear": -3700,
        "max31865_front": -16.15625,
        "max31865_rear": -16.5625,
        "sht31_inside": 24.683000564575195,
        "sht31_outside": 24.584999084472656,
        "time_s": 95.49
    },
    {
        "dac_front": -3700,
        "dac_rear": -3700,
        "max31865_front": -16.1875,
        "max31865_rear": -16.5625,
        "sht31_inside": 24.641000747680664,
        "sht31_outside": 24.54199981689453,
        "time_s": 98.501
    },
    {
        "dac_front": -3700,
        "dac_rear": -3700,
        "max31865_front": -16.15625,
        "max31865_rear": -16.5625,
        "sht31_inside": 24.569000244140625,
        "sht31_outside": 24.527999877929688,
        "time_s": 99.543
    },
    {
        "dac_front": -3700,
        "dac_rear": -3700,
        "max31865_front": -16.15625,
        "max31865_rear": -16.5625,
        "sht31_inside": 24.569000244140625,
        "sht31_outside": 24.62700080871582,
        "time_s": 100.555
    },
    {
        "dac_front": -3700,
        "dac_rear": -3700,
        "max31865_front": -16.1875,
        "max31865_rear": -16.5625,
        "sht31_inside": 24.611000061035156,
        "sht31_outside": 24.584999084472656,
        "time_s": 101.562
    },
    {
        "dac_front": -3700,
        "dac_rear": -3700,
        "max31865_front": -16.125,
        "max31865_rear": -16.53125,
        "sht31_inside": 24.55500030517578,
        "sht31_outside": 24.65399932861328,
        "time_s": 102.571
    },
    {
        "dac_front": -3700,
        "dac_rear": -3700,
        "max31865_front": -16.125,
        "max31865_rear": -16.5625,
        "sht31_inside": 24.569000244140625,
        "sht31_outside": 24.570999145507812,
        "time_s": 103.578
    },
    {
        "dac_front": -3700,
        "dac_rear": -3700,
        "max31865_front": -16.1875,
        "max31865_rear": -16.5625,
        "sht31_inside": 24.641000747680664,
        "sht31_outside": 24.55500030517578,
        "time_s": 104.585
    },
    {
        "dac_front": -3700,
        "dac_rear": -3700,
        "max31865_front": -16.15625,
        "max31865_rear": -16.5625,
        "sht31_inside": 24.69700050354004,
        "sht31_outside": 24.584999084472656,
        "time_s": 105.607
    },
    {
        "dac_front": -3700,
        "dac_rear": -3700,
        "max31865_front": -16.15625,
        "max31865_rear": -16.5,
        "sht31_inside": 24.69700050354004,
        "sht31_outside": 24.584999084472656,
        "time_s": 106.684
    },
    {
        "dac_front": -3700,
        "dac_rear": -3700,
        "max31865_front": -16.15625,
        "max31865_rear": -16.53125,
        "sht31_inside": 24.611000061035156,
        "sht31_outside": 24.570999145507812,
        "time_s": 107.621
    },
    {
        "dac_front": -3700,
        "dac_rear": -3700,
        "max31865_front": -16.1875,
        "max31865_rear": -16.5625,
        "sht31_inside": 24.584999084472656,
        "sht31_outside": 24.570999145507812,
        "time_s": 108.627
    },
    {
        "dac_front": -3700,
        "dac_rear": -3700,
        "max31865_front": -16.1875,
        "max31865_rear": -16.53125,
        "sht31_inside": 24.65399932861328,
        "sht31_outside": 24.597999572753906,
        "time_s": 109.632
    },
    {
        "dac_front": -3700,
        "dac_rear": -3700,
        "max31865_front": -16.15625,
        "max31865_rear": -16.53125,
        "sht31_inside": 24.683000564575195,
        "sht31_outside": 24.611000061035156,
        "time_s": 110.686
    },
    {
        "dac_front": -3700,
        "dac_rear": -3700,
        "max31865_front": -16.1875,
        "max31865_rear": -16.53125,
        "sht31_inside": 24.54199981689453,
        "sht31_outside": 24.570999145507812,
        "time_s": 111.692
    },
    {
        "dac_front": -3700,
        "dac_rear": -3700,
        "max31865_front": -16.1875,
        "max31865_rear": -16.5625,
        "sht31_inside": 24.625,
        "sht31_outside": 24.570999145507812,
        "time_s": 113.669
    },
    {
        "dac_front": -3700,
        "dac_rear": -3700,
        "max31865_front": -16.15625,
        "max31865_rear": -16.5625,
        "sht31_inside": 24.611000061035156,
        "sht31_outside": 24.597999572753906,
        "time_s": 114.661
    },
    {
        "dac_front": -3700,
        "dac_rear": -3700,
        "max31865_front": -16.21875,
        "max31865_rear": -16.53125,
        "sht31_inside": 24.625,
        "sht31_outside": 24.670000076293945,
        "time_s": 115.667
    },
    {
        "dac_front": -3700,
        "dac_rear": -3700,
        "max31865_front": -16.1875,
        "max31865_rear": -16.5625,
        "sht31_inside": 24.584999084472656,
        "sht31_outside": 24.641000747680664,
        "time_s": 116.671
    },
    {
        "dac_front": -3700,
        "dac_rear": -3700,
        "max31865_front": -16.1875,
        "max31865_rear": -16.5625,
        "sht31_inside": 24.625,
        "sht31_outside": 24.611000061035156,
        "time_s": 117.705
    },
    {
        "dac_front": -3700,
        "dac_rear": -3700,
        "max31865_front": -16.1875,
        "max31865_rear": -16.5625,
        "sht31_inside": 24.625,
        "sht31_outside": 24.584999084472656,
        "time_s": 118.699
    },
    {
        "dac_front": -3700,
        "dac_rear": -3700,
        "max31865_front": -16.125,
        "max31865_rear": -16.5625,
        "sht31_inside": 24.683000564575195,
        "sht31_outside": 24.570999145507812,
        "time_s": 119.706
    },
    {
        "dac_front": -3700,
        "dac_rear": -3700,
        "max31865_front": -16.1875,
        "max31865_rear": -16.5625,
        "sht31_inside": 24.611000061035156,
        "sht31_outside": 24.570999145507812,
        "time_s": 120.697
    },
    {
        "dac_front": -3700,
        "dac_rear": -3700,
        "max31865_front": -16.15625,
        "max31865_rear": -16.53125,
        "sht31_inside": 24.641000747680664,
        "sht31_outside": 24.54199981689453,
        "time_s": 121.702
    },
    {
        "dac_front": -3700,
        "dac_rear": -3700,
        "max31865_front": -16.1875,
        "max31865_rear": -16.5625,
        "sht31_inside": 24.54199981689453,
        "sht31_outside": 24.62700080871582,
        "time_s": 122.709
    },
    {
        "dac_front": -3700,
        "dac_rear": -3700,
        "max31865_front": -16.15625,
        "max31865_rear": -16.53125,
        "sht31_inside": 24.597999572753906,
        "sht31_outside": 24.670000076293945,
        "time_s": 123.715
    },
    {
        "dac_front": -3700,
        "dac_rear": -3700,
        "max31865_front": -16.1875,
        "max31865_rear": -16.5625,
        "sht31_inside": 24.66699981689453,
        "sht31_outside": 24.65399932861328,
        "time_s": 124.706
    },
    {
        "dac_front": -3700,
        "dac_rear": -3700,
        "max31865_front": -16.1875,
        "max31865_rear": -16.53125,
        "sht31_inside": 24.611000061035156,
        "sht31_outside": 24.55500030517578,
        "time_s": 125.744
    },
    {
        "dac_front": -3700,
        "dac_rear": -3700,
        "max31865_front": -16.1875,
        "max31865_rear": -16.5625,
        "sht31_inside": 24.597999572753906,
        "sht31_outside": 24.54199981689453,
        "time_s": 127.72
    },
    {
        "dac_front": -3700,
        "dac_rear": -3700,
        "max31865_front": -16.1875,
        "max31865_rear": -16.5625,
        "sht31_inside": 24.641000747680664,
        "sht31_outside": 24.584999084472656,
        "time_s": 128.747
    },
    {
        "dac_front": -3700,
        "dac_rear": -3700,
        "max31865_front": -16.1875,
        "max31865_rear": -16.53125,
        "sht31_inside": 24.611000061035156,
        "sht31_outside": 24.570999145507812,
        "time_s": 129.723
    },
    {
        "dac_front": -3700,
        "dac_rear": -3700,
        "max31865_front": -16.15625,
        "max31865_rear": -16.53125,
        "sht31_inside": 24.625,
        "sht31_outside": 24.611000061035156,
        "time_s": 130.729
    },
    {
        "dac_front": -3700,
        "dac_rear": -3700,
        "max31865_front": -16.1875,
        "max31865_rear": -16.5625,
        "sht31_inside": 24.611000061035156,
        "sht31_outside": 24.54199981689453,
        "time_s": 131.714
    },
    {
        "dac_front": -3700,
        "dac_rear": -3700,
        "max31865_front": -16.1875,
        "max31865_rear": -16.5625,
        "sht31_inside": 24.597999572753906,
        "sht31_outside": 24.597999572753906,
        "time_s": 132.758
    },
    {
        "dac_front": -3700,
        "dac_rear": -3700,
        "max31865_front": -16.1875,
        "max31865_rear": -16.5625,
        "sht31_inside": 24.499000549316406,
        "sht31_outside": 24.55500030517578,
        "time_s": 133.766
    },
    {
        "dac_front": -3700,
        "dac_rear": -3700,
        "max31865_front": -16.15625,
        "max31865_rear": -16.5625,
        "sht31_inside": 24.527999877929688,
        "sht31_outside": 24.584999084472656,
        "time_s": 134.757
    },
    {
        "dac_front": -3700,
        "dac_rear": -3700,
        "max31865_front": -16.1875,
        "max31865_rear": -16.53125,
        "sht31_inside": 24.499000549316406,
        "sht31_outside": 24.597999572753906,
        "time_s": 135.786
    },
    {
        "dac_front": -3700,
        "dac_rear": -3700,
        "max31865_front": -16.15625,
        "max31865_rear": -16.59375,
        "sht31_inside": 24.611000061035156,
        "sht31_outside": 24.570999145507812,
        "time_s": 136.772
    },
    {
        "dac_front": -3700,
        "dac_rear": -3700,
        "max31865_front": -16.15625,
        "max31865_rear": -16.53125,
        "sht31_inside": 24.597999572753906,
        "sht31_outside": 24.611000061035156,
        "time_s": 137.802
    },
    {
        "dac_front": -3700,
        "dac_rear": -3700,
        "max31865_front": -16.1875,
        "max31865_rear": -16.53125,
        "sht31_inside": 24.597999572753906,
        "sht31_outside": 24.641000747680664,
        "time_s": 138.777
    },
    {
        "dac_front": -3700,
        "dac_rear": -3700,
        "max31865_front": -16.15625,
        "max31865_rear": -16.5625,
        "sht31_inside": 24.486000061035156,
        "sht31_outside": 24.570999145507812,
        "time_s": 139.783
    },
    {
        "dac_front": -3700,
        "dac_rear": -3700,
        "max31865_front": -16.15625,
        "max31865_rear": -16.53125,
        "sht31_inside": 24.54199981689453,
        "sht31_outside": 24.597999572753906,
        "time_s": 140.773
    },
    {
        "dac_front": -3700,
        "dac_rear": -3700,
        "max31865_front": -16.15625,
        "max31865_rear": -16.53125,
        "sht31_inside": 24.472000122070312,
        "sht31_outside": 24.62700080871582,
        "time_s": 141.794
    },
    {
        "dac_front": -3700,
        "dac_rear": -3700,
        "max31865_front": -16.1875,
        "max31865_rear": -16.53125,
        "sht31_inside": 24.55500030517578,
        "sht31_outside": 24.499000549316406,
        "time_s": 142.854
    },
    {
        "dac_front": -3700,
        "dac_rear": -3700,
        "max31865_front": -16.1875,
        "max31865_rear": -16.5625,
        "sht31_inside": 24.569000244140625,
        "sht31_outside": 24.584999084472656,
        "time_s": 144.822
    },
    {
        "dac_front": -3700,
        "dac_rear": -3700,
        "max31865_front": -16.1875,
        "max31865_rear": -16.5625,
        "sht31_inside": 24.527999877929688,
        "sht31_outside": 24.55500030517578,
        "time_s": 145.829
    },
    {
        "dac_front": -3700,
        "dac_rear": -3700,
        "max31865_front": -16.1875,
        "max31865_rear": -16.5625,
        "sht31_inside": 24.584999084472656,
        "sht31_outside": 24.597999572753906,
        "time_s": 146.844
    },
    {
        "dac_front": -3700,
        "dac_rear": -3700,
        "max31865_front": -16.21875,
        "max31865_rear": -16.5625,
        "sht31_inside": 24.511999130249023,
        "sht31_outside": 24.62700080871582,
        "time_s": 147.836
    },
    {
        "dac_front": -3700,
        "dac_rear": -3700,
        "max31865_front": -16.125,
        "max31865_rear": -16.53125,
        "sht31_inside": 24.472000122070312,
        "sht31_outside": 24.472000122070312,
        "time_s": 148.859
    },
    {
        "dac_front": -3700,
        "dac_rear": -3700,
        "max31865_front": -16.15625,
        "max31865_rear": -16.53125,
        "sht31_inside": 24.499000549316406,
        "sht31_outside": 24.570999145507812,
        "time_s": 149.834
    },
    {
        "dac_front": -3700,
        "dac_rear": -3700,
        "max31865_front": -16.1875,
        "max31865_rear": -16.5625,
        "sht31_inside": 24.440000534057617,
        "sht31_outside": 24.597999572753906,
        "time_s": 150.819
    },
    {
        "dac_front": -3700,
        "dac_rear": -3700,
        "max31865_front": -16.1875,
        "max31865_rear": -16.5625,
        "sht31_inside": 24.472000122070312,
        "sht31_outside": 24.54199981689453,
        "time_s": 151.864
    },
    {
        "dac_front": -3700,
        "dac_rear": -3700,
        "max31865_front": -16.15625,
        "max31865_rear": -16.53125,
        "sht31_inside": 24.499000549316406,
        "sht31_outside": 24.44300079345703,
        "time_s": 152.871
    },
    {
        "dac_front": -3700,
        "dac_rear": -3700,
        "max31865_front": -16.1875,
        "max31865_rear": -16.53125,
        "sht31_inside": 24.511999130249023,
        "sht31_outside": 24.584999084472656,
        "time_s": 153.877
    },
    {
        "dac_front": -3700,
        "dac_rear": -3700,
        "max31865_front": -16.15625,
        "max31865_rear": -16.5625,
        "sht31_inside": 24.472000122070312,
        "sht31_outside": 24.499000549316406,
        "time_s": 155.922
    },
    {
        "dac_front": -3700,
        "dac_rear": -3700,
        "max31865_front": -16.1875,
        "max31865_rear": -16.5625,
        "sht31_inside": 24.511999130249023,
        "sht31_outside": 24.584999084472656,
        "time_s": 156.878
    },
    {
        "dac_front": -3700,
        "dac_rear": -3700,
        "max31865_front": -16.15625,
        "max31865_rear": -16.5625,
        "sht31_inside": 24.472000122070312,
        "sht31_outside": 24.570999145507812,
        "time_s": 157.884
    },
    {
        "dac_front": -3700,
        "dac_rear": -3700,
        "max31865_front": -16.1875,
        "max31865_rear": -16.5625,
        "sht31_inside": 24.440000534057617,
        "sht31_outside": 24.611000061035156,
        "time_s": 158.868
    },
    {
        "dac_front": -3700,
        "dac_rear": -3700,
        "max31865_front": -16.15625,
        "max31865_rear": -16.5625,
        "sht31_inside": 24.499000549316406,
        "sht31_outside": 24.62700080871582,
        "time_s": 159.897
    },
    {
        "dac_front": -3700,
        "dac_rear": -3700,
        "max31865_front": -16.15625,
        "max31865_rear": -16.5625,
        "sht31_inside": 24.427000045776367,
        "sht31_outside": 24.55500030517578,
        "time_s": 160.882
    },
    {
        "dac_front": -3700,
        "dac_rear": -3700,
        "max31865_front": -16.15625,
        "max31865_rear": -16.53125,
        "sht31_inside": 24.398000717163086,
        "sht31_outside": 24.641000747680664,
        "time_s": 161.912
    },
    {
        "dac_front": -3700,
        "dac_rear": -3700,
        "max31865_front": -16.15625,
        "max31865_rear": -16.53125,
        "sht31_inside": 24.371000289916992,
        "sht31_outside": 24.55500030517578,
        "time_s": 162.919
    },
    {
        "dac_front": -3700,
        "dac_rear": -3700,
        "max31865_front": -16.1875,
        "max31865_rear": -16.5625,
        "sht31_inside": 24.472000122070312,
        "sht31_outside": 24.584999084472656,
        "time_s": 163.941
    },
    {
        "dac_front": -3700,
        "dac_rear": -3700,
        "max31865_front": -16.15625,
        "max31865_rear": -16.53125,
        "sht31_inside": 24.371000289916992,
        "sht31_outside": 24.641000747680664,
        "time_s": 165.915
    },
    {
        "dac_front": -3700,
        "dac_rear": -3700,
        "max31865_front": -16.15625,
        "max31865_rear": -16.5625,
        "sht31_inside": 24.384000778198242,
        "sht31_outside": 24.641000747680664,
        "time_s": 166.943
    },
    {
        "dac_front": -3700,
        "dac_rear": -3700,
        "max31865_front": -16.21875,
        "max31865_rear": -16.5625,
        "sht31_inside": 24.486000061035156,
        "sht31_outside": 24.570999145507812,
        "time_s": 167.966
    },
    {
        "dac_front": -3700,
        "dac_rear": -3700,
        "max31865_front": -16.15625,
        "max31865_rear": -16.5625,
        "sht31_inside": 24.45599937438965,
        "sht31_outside": 24.683000564575195,
        "time_s": 168.973
    },
    {
        "dac_front": -3700,
        "dac_rear": -3700,
        "max31865_front": -16.1875,
        "max31865_rear": -16.5625,
        "sht31_inside": 24.486000061035156,
        "sht31_outside": 24.54199981689453,
        "time_s": 169.994
    },
    {
        "dac_front": -3700,
        "dac_rear": -3700,
        "max31865_front": -16.1875,
        "max31865_rear": -16.53125,
        "sht31_inside": 24.427000045776367,
        "sht31_outside": 24.55500030517578,
        "time_s": 170.997
    },
    {
        "dac_front": -3700,
        "dac_rear": -3700,
        "max31865_front": -16.1875,
        "max31865_rear": -16.5625,
        "sht31_inside": 24.45599937438965,
        "sht31_outside": 24.54199981689453,
        "time_s": 172.019
    },
    {
        "dac_front": -3700,
        "dac_rear": -3700,
        "max31865_front": -16.1875,
        "max31865_rear": -16.53125,
        "sht31_inside": 24.472000122070312,
        "sht31_outside": 24.62700080871582,
        "time_s": 173.054
    },
    {
        "dac_front": -3700,
        "dac_rear": -3700,
        "max31865_front": -16.15625,
        "max31865_rear": -16.53125,
        "sht31_inside": 24.527999877929688,
        "sht31_outside": 24.641000747680664,
        "time_s": 174.043
    },
    {
        "dac_front": -3700,
        "dac_rear": -3700,
        "max31865_front": -16.1875,
        "max31865_rear": -16.53125,
        "sht31_inside": 24.440000534057617,
        "sht31_outside": 24.683000564575195,
        "time_s": 175.049
    },
    {
        "dac_front": -3700,
        "dac_rear": -3700,
        "max31865_front": -16.1875,
        "max31865_rear": -16.53125,
        "sht31_inside": 24.398000717163086,
        "sht31_outside": 24.570999145507812,
        "time_s": 176.07
    },
    {
        "dac_front": -3700,
        "dac_rear": -3700,
        "max31865_front": -16.15625,
        "max31865_rear": -16.53125,
        "sht31_inside": 24.527999877929688,
        "sht31_outside": 24.584999084472656,
        "time_s": 177.086
    },
    {
        "dac_front": -3700,
        "dac_rear": -3700,
        "max31865_front": -16.1875,
        "max31865_rear": -16.53125,
        "sht31_inside": 24.427000045776367,
        "sht31_outside": 24.527999877929688,
        "time_s": 179.116
    },
    {
        "dac_front": -3700,
        "dac_rear": -3700,
        "max31865_front": -16.1875,
        "max31865_rear": -16.53125,
        "sht31_inside": 24.427000045776367,
        "sht31_outside": 24.65399932861328,
        "time_s": 180.095
    },
    {
        "dac_front": -3700,
        "dac_rear": -3700,
        "max31865_front": -16.1875,
        "max31865_rear": -16.53125,
        "sht31_inside": 24.55500030517578,
        "sht31_outside": 24.611000061035156,
        "time_s": 181.138
    },
    {
        "dac_front": -3700,
        "dac_rear": -3700,
        "max31865_front": -16.1875,
        "max31865_rear": -16.53125,
        "sht31_inside": 24.486000061035156,
        "sht31_outside": 24.527999877929688,
        "time_s": 182.123
    },
    {
        "dac_front": -3700,
        "dac_rear": -3700,
        "max31865_front": -16.1875,
        "max31865_rear": -16.5625,
        "sht31_inside": 24.569000244140625,
        "sht31_outside": 24.55500030517578,
        "time_s": 183.139
    },
    {
        "dac_front": -3700,
        "dac_rear": -3700,
        "max31865_front": -16.1875,
        "max31865_rear": -16.53125,
        "sht31_inside": 24.55500030517578,
        "sht31_outside": 24.55500030517578,
        "time_s": 184.139
    },
    {
        "dac_front": -3700,
        "dac_rear": -3700,
        "max31865_front": -16.1875,
        "max31865_rear": -16.5625,
        "sht31_inside": 24.55500030517578,
        "sht31_outside": 24.611000061035156,
        "time_s": 185.116
    },
    {
        "dac_front": -3700,
        "dac_rear": -3700,
        "max31865_front": -16.15625,
        "max31865_rear": -16.5625,
        "sht31_inside": 24.472000122070312,
        "sht31_outside": 24.584999084472656,
        "time_s": 186.141
    },
    {
        "dac_front": -3700,
        "dac_rear": -3700,
        "max31865_front": -16.125,
        "max31865_rear": -16.5,
        "sht31_inside": 24.55500030517578,
        "sht31_outside": 24.570999145507812,
        "time_s": 187.145
    },
    {
        "dac_front": -3700,
        "dac_rear": -3700,
        "max31865_front": -16.1875,
        "max31865_rear": -16.5625,
        "sht31_inside": 24.54199981689453,
        "sht31_outside": 24.584999084472656,
        "time_s": 188.172
    },
    {
        "dac_front": -3700,
        "dac_rear": -3700,
        "max31865_front": -16.15625,
        "max31865_rear": -16.5625,
        "sht31_inside": 24.641000747680664,
        "sht31_outside": 24.511999130249023,
        "time_s": 189.183
    },
    {
        "dac_front": -3700,
        "dac_rear": -3700,
        "max31865_front": -16.1875,
        "max31865_rear": -16.53125,
        "sht31_inside": 24.54199981689453,
        "sht31_outside": 24.683000564575195,
        "time_s": 190.171
    },
    {
        "dac_front": -3700,
        "dac_rear": -3700,
        "max31865_front": -16.1875,
        "max31865_rear": -16.5625,
        "sht31_inside": 24.54199981689453,
        "sht31_outside": 24.597999572753906,
        "time_s": 191.183
    },
    {
        "dac_front": -3700,
        "dac_rear": -3700,
        "max31865_front": -16.15625,
        "max31865_rear": -16.59375,
        "sht31_inside": 24.641000747680664,
        "sht31_outside": 24.597999572753906,
        "time_s": 192.192
    },
    {
        "dac_front": -3700,
        "dac_rear": -3700,
        "max31865_front": -16.1875,
        "max31865_rear": -16.5625,
        "sht31_inside": 24.398000717163086,
        "sht31_outside": 24.55500030517578,
        "time_s": 194.226
    },
    {
        "dac_front": -3700,
        "dac_rear": -3700,
        "max31865_front": -16.1875,
        "max31865_rear": -16.53125,
        "sht31_inside": 24.55500030517578,
        "sht31_outside": 24.570999145507812,
        "time_s": 195.212
    },
    {
        "dac_front": -3700,
        "dac_rear": -3700,
        "max31865_front": -16.1875,
        "max31865_rear": -16.53125,
        "sht31_inside": 24.472000122070312,
        "sht31_outside": 24.670000076293945,
        "time_s": 196.218
    },
    {
        "dac_front": -3700,
        "dac_rear": -3700,
        "max31865_front": -16.15625,
        "max31865_rear": -16.53125,
        "sht31_inside": 24.569000244140625,
        "sht31_outside": 24.69700050354004,
        "time_s": 197.239
    },
    {
        "dac_front": -3700,
        "dac_rear": -3700,
        "max31865_front": -16.15625,
        "max31865_rear": -16.5,
        "sht31_inside": 24.486000061035156,
        "sht31_outside": 24.69700050354004,
        "time_s": 198.268
    },
    {
        "dac_front": -3700,
        "dac_rear": -3700,
        "max31865_front": -16.15625,
        "max31865_rear": -16.53125,
        "sht31_inside": 24.55500030517578,
        "sht31_outside": 24.670000076293945,
        "time_s": 199.261
    },
    {
        "dac_front": -3700,
        "dac_rear": -3700,
        "max31865_front": -16.15625,
        "max31865_rear": -16.53125,
        "sht31_inside": 24.472000122070312,
        "sht31_outside": 24.570999145507812,
        "time_s": 200.362
    },
    {
        "dac_front": -3700,
        "dac_rear": -3700,
        "max31865_front": -16.15625,
        "max31865_rear": -16.53125,
        "sht31_inside": 24.472000122070312,
        "sht31_outside": 24.499000549316406,
        "time_s": 201.243
    }
]
